sideload_nu_0_bin_6633e4fae41b4d34e4eddc2a/__init__.py
sideload_nu_0_bin_6633e4fae41b4d34e4eddc2a/nu-0.93.0-x86_64-pc-windows-msvc.zip
sideload_nu_0_bin_6633e4fae41b4d34e4eddc2a-1.0.0.dist-info/METADATA
sideload_nu_0_bin_6633e4fae41b4d34e4eddc2a-1.0.0.dist-info/WHEEL
sideload_nu_0_bin_6633e4fae41b4d34e4eddc2a-1.0.0.dist-info/top_level.txt
sideload_nu_0_bin_6633e4fae41b4d34e4eddc2a-1.0.0.dist-info/RECORD
